nonebot_plugin_guild_patch/__init__.py
nonebot_plugin_guild_patch/models.py
nonebot_plugin_guild_patch/permission.py
nonebot_plugin_guild_patch-0.2.2.dist-info/LICENSE
nonebot_plugin_guild_patch-0.2.2.dist-info/WHEEL
nonebot_plugin_guild_patch-0.2.2.dist-info/METADATA
nonebot_plugin_guild_patch-0.2.2.dist-info/RECORD
