Metadata-Version: 2.1
Name: nonebot-plugin-guild-patch
Version: 0.2.2
Summary: Patch plugin for NoneBot2 QQ guild (go-cqhttp) support.
Home-page: https://github.com/mnixry/nonebot-plugin-guild-patch
License: MIT
Author: Mix
Author-email: mnixry@users.noreply.github.com
Requires-Python: >=3.7.3,<4.0.0
Classifier: License :: OSI Approved :: MIT License
Classifier: Programming Language :: Python :: 3
Classifier: Programming Language :: Python :: 3.8
Classifier: Programming Language :: Python :: 3.9
Classifier: Programming Language :: Python :: 3.10
Classifier: Programming Language :: Python :: 3.11
Requires-Dist: nonebot-adapter-onebot (>=2.1.0,<3.0.0)
Requires-Dist: nonebot2 (>=2.0.0-beta.1,<3.0.0)
Project-URL: Repository, https://github.com/mnixry/nonebot-plugin-guild-patch
